setup.cfg
setup.py
pybuilder_nose/__init__.py
pybuilder_nose/tasks.py
pybuilder_nose/utils.py
pybuilder_nose.egg-info/PKG-INFO
pybuilder_nose.egg-info/SOURCES.txt
pybuilder_nose.egg-info/dependency_links.txt
pybuilder_nose.egg-info/entry_points.txt
pybuilder_nose.egg-info/requires.txt
pybuilder_nose.egg-info/top_level.txt
pybuilder_nose.egg-info/zip-safe