Metadata-Version: 1.1
Name: pybuilder-nose
Version: 0.0.4
Summary: PyBuilder Nose Plugin
Home-page: https://github.com/alex-dow/pybuilder_nose
Author: Alex Dowgailenko
Author-email: adow@psikon.com
License: Apache License, Version 2.0
Platform: UNKNOWN
Classifier: Development Status :: 3 - Alpha
Classifier: Environment :: Console
Classifier: Intended Audience :: Developers
Classifier: License :: OSI Approved :: Apache Software License
Classifier: Programming Language :: Python
Classifier: Programming Language :: Python :: 2
Classifier: Programming Language :: Python :: 2.7
